{
  "type": "compositegear:armor",
  "slot": "head",
  "id": "ushanka_hat",
  "durability": 256,
  "material" : {
    "type": "generic",
    "protection": 1,
    "enchantability": 15
  },
  "attributes": [
    {
      "type": "intelligence",
      "class": "CLOTHING",
      "hasDescription": true,
      "hasVisualAttributes": true
    },
    {
      "type": "colorable",
      "defaultColor": 8487297
    },
    {
      "type": "warm"
    },
    {
      "type": "satiety_save_cold"
    }
  ],
  "model" : {
    "type": "variant_type",
    "path": "items/clothing",
    "variant": "ushanka_hat"
  },
  "armorModel" : {
    "armorName": "ushanka_hat",
    "hasOverlay": true
  }
}
