{
  "type": "forge:ore_shaped",
  "pattern": [
    "PIP",
    "ALA",
    "AAA"
  ],
  "conditions": [
    {
      "type": "compositegear:mod_loaded",
      "modid": "ic2"
    },
    {
      "type": "compositegear:crafting_allowed",
      "key": "composite_chestplate"
    }
  ],
  "key": {
    "A": {
      "type": "compositegear:ic2_ingredient",
      "name": "crafting#alloy"
    },
    "I": {
      "item": "minecraft:iron_chestplate"
    },
    "L": {
      "item": "minecraft:leather_chestplate"
    },
    "P": {
      "item": "compositegear:composite_pauldron"
    }
  },
  "result": {
    "item": "compositegear:composite_chestplate"
  }
}