{
  "type": "forge:ore_shaped",
  "pattern": [
    "RFR",
    "SGS",
    "RMR"
  ],
  "conditions": [
    {
      "type": "compositegear:mod_loaded",
      "modid": "techreborn"
    },
    {
      "type": "compositegear:crafting_allowed",
      "key": "respirator_mask_composite"
    }
  ],
  "key": {
    "G": {
      "item": "techreborn:reinforced_glass"
    },
    "F": {
      "item": "compositegear:composite_faceplate"
    },
    "M": {
      "item": "compositegear:air_mask_module"
    },
    "R": {
      "type": "forge:ore_dict",
      "ore": "itemRubber"
    },
    "S": {
      "item": "minecraft:string"
    }
  },
  "result": {
    "item": "compositegear:respirator_mask_composite"
  }
}